ior/__init__.py
ior/iorsdk.py
ior/client/__init__.py
ior/client/certificate_service.py
ior/client/contract_template_service.py
ior/client/exchange_service.py
ior/client/permission_control_service.py
ior/client/role_control_service.py
ior/client/template_control_service.py
ior/client/vote_delegation_template_service.py
ior/client/vote_template_service.py
ior/util/__init__.py
ior/util/result_utils.py
ior/util/web3_utils.py
test/__init__.py
test/test_cert.py
test/test_role.py
test/test_template.py
iorclient-1.0.4.dist-info/LICENSE
iorclient-1.0.4.dist-info/METADATA
iorclient-1.0.4.dist-info/WHEEL
iorclient-1.0.4.dist-info/top_level.txt
iorclient-1.0.4.dist-info/RECORD
