Metadata-Version: 2.1
Name: iorclient
Version: 1.0.4
Summary: ior client sdk for ior standard
Home-page: https://github.com/tzspace-ior/iorclient
Author: Jie Guan
Author-email: jguanisme@163.com
Classifier: Programming Language :: Python :: 3
Classifier: License :: OSI Approved :: MIT License
Classifier: Operating System :: OS Independent
License-File: LICENSE
